LICENSE
MANIFEST.in
README.md
setup.py
cloud_functions_dispatch/__init__.py
cloud_functions_dispatch/f.py
cloud_functions_dispatch.egg-info/PKG-INFO
cloud_functions_dispatch.egg-info/SOURCES.txt
cloud_functions_dispatch.egg-info/dependency_links.txt
cloud_functions_dispatch.egg-info/requires.txt
cloud_functions_dispatch.egg-info/top_level.txt
docs/Makefile
docs/make.bat
docs/build/doctrees/considerations.doctree
docs/build/doctrees/contributing.doctree
docs/build/doctrees/environment.pickle
docs/build/doctrees/index.doctree
docs/build/doctrees/installation.doctree
docs/build/doctrees/overview.doctree
docs/build/doctrees/security.doctree
docs/build/doctrees/usage.doctree
docs/build/html/.buildinfo
docs/build/html/considerations.html
docs/build/html/contributing.html
docs/build/html/genindex.html
docs/build/html/index.html
docs/build/html/installation.html
docs/build/html/objects.inv
docs/build/html/overview.html
docs/build/html/search.html
docs/build/html/searchindex.js
docs/build/html/security.html
docs/build/html/usage.html
docs/build/html/_sources/considerations.rst.txt
docs/build/html/_sources/contributing.rst.txt
docs/build/html/_sources/index.rst.txt
docs/build/html/_sources/installation.rst.txt
docs/build/html/_sources/overview.rst.txt
docs/build/html/_sources/security.rst.txt
docs/build/html/_sources/usage.rst.txt
docs/build/html/_static/alabaster.css
docs/build/html/_static/basic.css
docs/build/html/_static/custom.css
docs/build/html/_static/doctools.js
docs/build/html/_static/documentation_options.js
docs/build/html/_static/file.png
docs/build/html/_static/jquery-3.4.1.js
docs/build/html/_static/jquery.js
docs/build/html/_static/language_data.js
docs/build/html/_static/minus.png
docs/build/html/_static/plus.png
docs/build/html/_static/pygments.css
docs/build/html/_static/searchtools.js
docs/build/html/_static/underscore-1.3.1.js
docs/build/html/_static/underscore.js
docs/source/conf.py
docs/source/considerations.rst
docs/source/contributing.rst
docs/source/index.rst
docs/source/installation.rst
docs/source/overview.rst
docs/source/security.rst
docs/source/usage.rst