Metadata-Version: 2.1
Name: cloud-functions-dispatch
Version: 0.9.1
Summary: Dispatches decorated in-process function calls to cloud function for execution
Home-page: https://github.com/seawolf42/cloud-functions-dispatch
Author: jeffrey k eliasen
Author-email: jeff@jke.net
License: MIT License
Keywords: cloud functions
Platform: UNKNOWN
Classifier: Development Status :: 4 - Beta
Classifier: Intended Audience :: Developers
Classifier: Intended Audience :: Financial and Insurance Industry
Classifier: License :: OSI Approved :: MIT License
Classifier: Programming Language :: Python :: 3 :: Only
Classifier: Programming Language :: Python :: 3.7
Classifier: Programming Language :: Python :: 3.8
Classifier: Topic :: Software Development :: Libraries
Classifier: Topic :: System :: Distributed Computing
Requires-Python: >=3.7
